test_dev/__init__.py
test_dev/_nbdev.py
test_dev/core.py
test_dev-0.0.3.dist-info/LICENSE
test_dev-0.0.3.dist-info/METADATA
test_dev-0.0.3.dist-info/WHEEL
test_dev-0.0.3.dist-info/entry_points.txt
test_dev-0.0.3.dist-info/top_level.txt
test_dev-0.0.3.dist-info/RECORD
