Metadata-Version: 2.1
Name: test-dev
Version: 0.0.3
Summary: this is a test site for dev https://jkabc123.github.io/test_dev/
Home-page: https://github.com/jkabc123/test_dev
Author: Peter Yang
Author-email: yang.piyi@gmail.com
License: Apache Software License 2.0
Keywords: test,dev,demo
Platform: UNKNOWN
Classifier: Development Status :: 3 - Alpha
Classifier: Intended Audience :: Developers
Classifier: License :: OSI Approved :: Apache Software License
Classifier: Natural Language :: English
Classifier: Programming Language :: Python :: 3.6
Classifier: Programming Language :: Python :: 3.7
Classifier: Programming Language :: Python :: 3.8
Requires-Python: >=3.6
